ohmytmp_plugins/destination/__init__.py
ohmytmp_plugins/destination/dst.py
ohmytmp_destination-0.0.2.dist-info/LICENSE
ohmytmp_destination-0.0.2.dist-info/METADATA
ohmytmp_destination-0.0.2.dist-info/WHEEL
ohmytmp_destination-0.0.2.dist-info/top_level.txt
ohmytmp_destination-0.0.2.dist-info/RECORD
